<?xml version='1.0' encoding='utf-8'?>
<common_sequences><sequence value="लड़िक"><word><root>लड़िका</root><category>Noun_m_e1</category><word_forms>लड़िको/लड़िकौ/लड़िकउ, लड़िकनो/लड़िकनौ/लड़िकनउ, लड़िको/लड़िकौ/लड़िकउ, लड़िकनौ/लड़िकनो/लड़िकनउ</word_forms></word></sequence><sequence value="राज"><word><root>राजा</root><category>Noun_m_e1</category><word_forms>राजो/राजौ/राजउ, राजो/राजौ/राजउ, राजो/राजौ/राजउ, राजनो/राजनौ/राजनउ</word_forms></word></sequence><sequence value="घर"><word><root>घर</root><category>Noun_m_e1</category><word_forms>घरो/घरौ/घरउ, घरो/घरौ/घरउ, घरो/घरौ/घरउ, घरनो/घरनौ/घरनउ</word_forms></word></sequence><sequence value="खर्च"><word><root>खर्च</root><category>Noun_m_e1</category><word_forms>खर्चो/खर्चौ/खर्चउ, खर्चो/खर्चौ/खर्चउ, खर्चो/खर्चौ/खर्चउ, खर्चनो/खर्चनौ/खर्चनउ</word_forms></word></sequence><sequence value="कवि"><word><root>कवि</root><category>Noun_m_e1</category><word_forms>कविओ/कविअउ/कविऔ, कविओ/कविअउ/कविऔ, कविओ/कविअउ/कविऔ, कविनो/कविनउ/कविनौ</word_forms></word></sequence><sequence value="आदम"><word><root>आदमी</root><category>Noun_m</category><word_forms>आदमी, आदमी, आदमी, आदमिन</word_forms></word></sequence><sequence value="सत्रु"><word><root>सत्रु</root><category>Noun_m_e1</category><word_forms>सत्रुओ/सत्रुअउ/सत्रुऔ, सत्रुओ/सत्रुअउ/सत्रुऔ, सत्रुओ/सत्रुअउ/सत्रुऔ, सत्रुनो/सत्रुनउ/सत्रुनौ</word_forms></word></sequence><sequence value="आल"><word><root>आलू</root><category>Noun_m</category><word_forms>आलू, आलू, आलू, आलुन</word_forms></word></sequence><sequence value="कुव"><word><root>कुवाँ</root><category>Noun_m_e1</category><word_forms>कुवों/कुवौं/कुवउं/कुवोँ/कुवौँ/कुवउँ/कुओं/कुऔं/कुअंउ/कुओँ/कुऔँ/कुअँउ, कुवों/कुवौं/कुवउं/कुवोँ/कुवौँ/कुवउँ/कुओं/कुऔं/कुअंउ/कुओँ/कुऔँ/कुअँउ, कुवों/कुवौं/कुवउं/कुवोँ/कुवौँ/कुवउँ/कुओं/कुऔं/कुअंउ/कुओँ/कुऔँ/कुअँउ, कुवँनउ/कुवंनउ/कुंवनो/कुंवनौ/कुँवनो/कुँवनौ/कुअँनो/कुअंनो/कुअँनउ/कुअंनउ/कुअँनौ/कुअंनौ</word_forms></word></sequence><sequence value="गेह"><word><root>गेहूँ</root><category>Noun_m_e1</category><word_forms>गेहूँओ/गेहूंओ/गेहूँऔ/गेहूंऔ/गेहूँअउ/गेहूंअउ, गेहूँओ/गेहूंओ/गेहूँऔ/गेहूंऔ/गेहूँअउ/गेहूंअउ, गेहूँओ/गेहूंओ/गेहूँऔ/गेहूंऔ/गेहूँअउ/गेहूंअउ, गेहुँनो/गेहुंनो/गेहुँनउ/गेहुंनउ/गेहुँनौ/गेहुंनौ</word_forms></word></sequence><sequence value="क्रोध"><word><root>क्रोध</root><category>Noun_m</category><word_forms>क्रोध, क्रोध, क्रोध, क्रोध</word_forms></word></sequence><sequence value="लकठ"><word><root>लकठो</root><category>Noun_m_e1</category><word_forms>लकठो/लकठउ/लकठौ, लकठनो/लकठोनो/लकठनउ/लकठोनउ/लकठनौ/लकठोनौ, लकठो/लकठउ/लकठौ, लकठनो/लकठोनो/लकठनउ/लकठोनउ/लकठनौ/लकठोनौ</word_forms></word></sequence><sequence value="सरसों"><word><root>सरसों</root><category>Noun_m_e1</category><word_forms>सरसोंओं/सरसोँओँ/सरसोंऔं/सरसोँऔँ/सरसोंअउं/सरसोँअउँ, सरसोंनो/सरसोँनउ/सरसंनउ/सरसँनउ/सरसंनौ/सरसँनौ, सरसोंओं/सरसोँओँ/सरसोंऔं/सरसोँऔँ/सरसोंअउं/सरसोँअउँ, सरसोंनो/सरसोँनो/सरसंनउ/सरसँनउ/सरसंनौ/सरसँनौ</word_forms></word></sequence><sequence value="गोसाईं"><word><root>गोसाईं</root><category>Noun_m_e1</category><word_forms>गोसाईंओ/गोसाईँओ/गोसाईंअउं/गोसाईँअउँ/गोसाईंऔं/गोसाईँऔँ, गोसाईंओ/गोसाईँओ/गोसाईंअउं/गोसाईँअउँ/गोसाईंऔं/गोसाईँऔँ, गोसाईंओ/गोसाईँओ/गोसाईंअउं/गोसाईँअउँ/गोसाईंऔं/गोसाईँऔँ, गोसाईंअनउ/गोसाईँअनउ/गोसाईंअनो/गोसाईँअनो/गोसाईंअनौ/गोसाईँअनौ</word_forms></word></sequence><sequence value="सोनर"><word><root>सोनरा</root><category>Noun_m_e1</category><word_forms>सोनरो/सोनरउ/सोनरौ, सोनरो/सोनरउ/सोनरौ, सोनरो/सोनरउ/सोनरौ, सोनरनउ/सोनरनो/सोनरनौ</word_forms></word></sequence><sequence value="आदमि"><word><root>आदमी</root><category>Noun_m_e1</category><word_forms>आदमिओ/आदमिअउ/आदमिऔ, आदमिओ/आदमिअउ/आदमिऔ, आदमिओ/आदमिअउ/आदमिऔ, आदमिनउ/आदमिनो/आदमिनौ</word_forms></word></sequence><sequence value="आलु"><word><root>आलू</root><category>Noun_m_e1</category><word_forms>आलुओ/आलुअउ/आलुऔ, आलुओ/आलुअउ/आलुऔ, आलुओ/आलुअउ/आलुऔ, आलुनउ/आलुनो/आलुनौ</word_forms></word></sequence><sequence value="क्रोधे/क्रोधै/क्रोधइ"><word><root>क्रोध</root><category>Noun_m_e</category><word_forms>क्रोधे/क्रोधै/क्रोधइ, क्रोधे/क्रोधै/क्रोधइ, क्रोधे/क्रोधै/क्रोधइ, क्रोधे/क्रोधै/क्रोधइ</word_forms></word></sequence><sequence value="क्रोधो/क्रोधौ/क्रोधउ"><word><root>क्रोध</root><category>Noun_m_e1</category><word_forms>क्रोधो/क्रोधौ/क्रोधउ, क्रोधो/क्रोधौ/क्रोधउ, क्रोधो/क्रोधौ/क्रोधउ, क्रोधो/क्रोधौ/क्रोधउ</word_forms></word></sequence><sequence value="लड़क"><word><root>लड़की</root><category>Noun_f</category><word_forms>लड़की, लड़किन, लड़की, लड़किन</word_forms></word></sequence><sequence value="मा"><word><root>मांयनइ</root><category>Noun_f_e</category><word_forms>मांयनै, मांयने, माँइने, माँइनइ</word_forms></word></sequence><sequence value="रात"><word><root>राते</root><category>Noun_f_e</category><word_forms>रातइ, रातै, रातने, रातनइ</word_forms></word></sequence><sequence value="राति"><word><root>रातिए</root><category>Noun_f_e</category><word_forms>रातिए, रातिअइ, रातिने, रातिनइ</word_forms></word></sequence><sequence value="औरत"><word><root>औरते</root><category>Noun_f_e</category><word_forms>औरतइ, औरतै, औरतने, औरतनइ</word_forms></word></sequence><sequence value="भास"><word><root>भासे</root><category>Noun_f_e</category><word_forms>भासइ, भासै, भासने, भासनइ</word_forms></word></sequence><sequence value="गुड़िय"><word><root>गुड़िया</root><category>Noun_f</category><word_forms>गुड़िया/गुड़िआ, गुड़िया/गुड़िआ, गुड़िया/गुड़िआ, गुड़ियन/गुड़िअन</word_forms></word></sequence><sequence value="सक्ति"><word><root>सक्तिअइ</root><category>Noun_f_e</category><word_forms>सक्तिऐ, सक्तिने, सक्तिनइ, सक्तिनऐ</word_forms></word></sequence><sequence value="ऋतु"><word><root>ऋतुअइ</root><category>Noun_f_e</category><word_forms>ऋतुऐ, ऋतुने, ऋतुअनइ, ऋतुनै</word_forms></word></sequence><sequence value="बह"><word><root>बहू</root><category>Noun_f</category><word_forms>बहू, बहुन, बहू, बहुन</word_forms></word></sequence><sequence value="लौ"><word><root>लौअइ</root><category>Noun_f_e</category><word_forms>लौऐ, लौने, लौनइ, लौनै</word_forms></word></sequence><sequence value="माँ"><word><root>माँ</root><category>Noun_f</category><word_forms>माँ/मां, माँवन/माँयन/माँइन/मांवन/मांयन/मांँइन, माँ/मां, माँवन/माँयन/माँइन/मांवन/मांयन/मांँइन</word_forms></word></sequence><sequence value="फोटो"><word><root>फोटोंअइ</root><category>Noun_f_e</category><word_forms>फोटोंऐ, फोटोँने, फोटोँनइ, फोटोँनै</word_forms></word></sequence><sequence value="फोटों"><word><root>फोटों</root><category>Noun_f</category><word_forms>फोटों/फोटोँ, फोटों/फोटोँ, फोटों/फोटोँ, फोटोंन/फोटोँन</word_forms></word></sequence><sequence value="भूइं"><word><root>भूइं</root><category>Noun_f</category><word_forms>भूइं/भूइँ/भूईं/भूईँ, भूइंअन/भूइँअन/भूईंन/भूईँन, भूइं/भूइँ/भूईं/भूईँ, भूइंअन/भूइँअन/भूईंन/भूईँन</word_forms></word></sequence><sequence value="भौं"><word><root>भौं</root><category>Noun_f</category><word_forms>भौं/भौँ, भौंअन/भौँअन/भँउअन/भंउअन, भौं/भौँ, भौंअन/भौँअन/भँउअन/भंउअन</word_forms></word></sequence><sequence value="भरसा"><word><root>भरसाईं</root><category>Noun_f</category><word_forms>भरसाईं/भरसाईँ, भरसाइंन/बरसाइँन, भरसाईं/भरसाईँ, भरसाइंन/बरसाइँन</word_forms></word></sequence><sequence value="भोर"><word><root>भोरइ</root><category>Noun_f_e</category><word_forms>भोरै, भोरने, भोरनइ, भोरनै</word_forms></word></sequence><sequence value="लड़कि"><word><root>लड़की</root><category>Noun_f_e</category><word_forms>लड़किए, लड़किअइ, लड़किऐ, लड़किने</word_forms></word></sequence><sequence value="म"><word><root>माई</root><category>Noun_f_e</category><word_forms>माइए, मइए, मइअइ, मइऐ</word_forms></word></sequence><sequence value="गुड़ि"><word><root>गुड़ियने</root><category>Noun_f_e</category><word_forms>गुड़िअनइ, गुड़िअने, गुड़ियनै, गुड़िअनै</word_forms></word></sequence><sequence value="बहु"><word><root>बहुअइ</root><category>Noun_f_e</category><word_forms>बहुऐ, बहुने, बहुनइ, बहुनै</word_forms></word></sequence><sequence value="फोट"><word><root>फोटोनइ</root><category>Noun_f_e</category><word_forms>फोटोनै, फोटों, फोटोँए, फोटँअइ</word_forms></word></sequence><sequence value="भूइ"><word><root>भूइँऐ</root><category>Noun_f_e</category><word_forms>भूइंअने, भूइँअने, भूइंअनइ, भूइँअनइ</word_forms></word></sequence><sequence value="भौ"><word><root>भौँउऐ</root><category>Noun_f_e</category><word_forms>भौंउऐ, भौंअइ, भौँअइ, भौँउअइ</word_forms></word></sequence><sequence value="भ"><word><root>भौंअनै</root><category>Noun_f_e</category><word_forms>भौँअनै, भँउअनै, भंउअनै, भरसाईं</word_forms></word></sequence><sequence value="भरस"><word><root>भरसइंअइं</root><category>Noun_f_e</category><word_forms>भरसइँअइँ, भरसाइंऐं, भरसाइँऐँ, भरसाइंने</word_forms></word></sequence><sequence value="भरसइ"><word><root>भरसाइँनइँ</root><category>Noun_f_e</category><word_forms>भरसइंने, भरसइँने, भरसइंनइं, भरसइँनइँ</word_forms></word></sequence><sequence value="लड़किय"><word><root>लड़किया</root><category>Noun_f_rednt_e1</category><word_forms>लड़कियो/लड़कियौ/लड़कियउ, लड़कियनो/लड़कियनौ/लड़कियनउ/लड़किअनो/लड़किअनौ/लड़किअनउ, लड़कियो/लड़कियौ/लड़कियउ, लड़कियनो/लड़कियनौ/लड़कियनउ/लड़किअनो/लड़किअनौ/लड़किअनउ</word_forms></word></sequence><sequence value="मइय"><word><root>मइया</root><category>Noun_f_rednt_e1</category><word_forms>मइयो/मइयौ/मइयउ/मइओ/मइअउ/मइऔ, मइयनो/मइयनौ/मइयनउ/मइअनो/मइअनौ/मइअनउ, मइयो/मइयौ/मइयउ/मइओ/मइअउ/मइऔ, मइयनो/मइयनौ/मइयनउ/मइअनो/मइअनौ/मइअनउ</word_forms></word></sequence><sequence value="रतिय"><word><root>रतिया</root><category>Noun_f_rednt_e1</category><word_forms>रतियो/रतियौ/रतियउ/रतिओ/रतिअउ/रतिऔ, रतियो/रतियौ/रतियउ/रतिओ/रतिअउ/रतिऔ, रतियो/रतियौ/रतियउ/रतिओ/रतिअउ/रतिऔ, रतियनो/रतियनौ/रतियनउ/रतिअनो/रतिअनौ/रतिअनउ</word_forms></word></sequence><sequence value="औरतिय"><word><root>औरतिया</root><category>Noun_f_rednt_e1</category><word_forms>औरतियो/औरतियौ/औरतियउ/औरतिओ/औरतिऔ/औरतिअउ, औरतियनो/औरतियनौ/औरतियनउ/औरतिअनो/औरतिअनौ/औरतिअनउ, औरतियो/औरतियौ/औरतियउ/औरतिओ/औरतिऔ/औरतिअउ, औरतियनो/औरतियनौ/औरतियनउ/औरतिअनो/औरतिअनौ/औरतिअनउ</word_forms></word></sequence><sequence value="भसव"><word><root>भसवा</root><category>Noun_f_rednt_e1</category><word_forms>भसवो/भसवौ/भसवउ, भसवो/भसवौ/भसवउ, भसवो/भसवौ/भसवउ, भसवनो/भसवनौ/भसवनउ</word_forms></word></sequence><sequence value="लउव"><word><root>लउवा</root><category>Noun_f_rednt_e1</category><word_forms>लउवो/लउवउ/लउवौ/लउओ/लउअउ/लउऔ, लउवनो/लउअनो/लउवनउ/लउअनउ/लउवनौ/लउअनौ/, लउवो/लउवउ/लउवौ/लउओ/लउअउ/लउऔ, लउवनो/लउअनो/लउवनउ/लउअनउ/लउवनौ/लउअनौ/</word_forms></word></sequence><sequence value="गुड़ियव"><word><root>गुड़ियवा</root><category>Noun_f_rednt_e1</category><word_forms>गुड़ियवो/गुड़िअवो/गुड़ियवउ/गुड़िअवउ/गुड़ियवौ/गुड़िअवौ, गुड़ियवो/गुड़िअवो/गुड़ियवउ/गुड़िअवउ/गुड़ियवौ/गुड़िअवौ, गुड़ियवो/गुड़िअवो/गुड़ियवउ/गुड़िअवउ/गुड़ियवौ/गुड़िअवौ, गुड़ियवनो/गुड़ियवनौ/गुड़ियवनउ/गुड़िअवनो/गुड़िअवनउ/गुड़िअवनौ</word_forms></word></sequence><sequence value="सक्तिय"><word><root>सक्तिया</root><category>Noun_f_rednt_e1</category><word_forms>सक्तियो/सक्तियौ/सक्तियउ, सक्तियो/सक्तियौ/सक्तियउ, सक्तियो/सक्तियौ/सक्तियउ, सक्तियनो/सक्तियनौ/सक्तियनउ</word_forms></word></sequence><sequence value="ऋतुव"><word><root>ऋतुवा</root><category>Noun_f_rednt_e1</category><word_forms>ऋतुवो/ऋतुवौ/ऋतुवउ, ऋतुवो/ऋतुवौ/ऋतुवउ, ऋतुवो/ऋतुवौ/ऋतुवउ, ऋतुवनो/ऋतुवनौ/ऋतुवनउ</word_forms></word></sequence><sequence value="बहुव"><word><root>बहुवा</root><category>Noun_f_rednt_e1</category><word_forms>बहुवो/बहुवौ/बहुवउ, बहुवो/बहुवौ/बहुवउ, बहुवो/बहुवौ/बहुवउ, बहुवनो/बहुवनौ/बहुवनउ</word_forms></word></sequence><sequence value="भोरव"><word><root>भोरवा</root><category>Noun_f_rednt_e1</category><word_forms>भोरवो/भोरवौ/भोरवउ, भोरवो/भोरवौ/भोरवउ, भोरवो/भोरवौ/भोरवउ, भोरवनो/भोरवनौ/भोरवनउ</word_forms></word></sequence><sequence value="भरसइंय"><word><root>भरसइंयां</root><category>Noun_f_rednt_e1</category><word_forms>भरसइंयों/भरसइंयौं/भरसइंयउं/भरसइंयोँ/भरसइंयौँ/भरसइंयउँ/भरसइँयों/भरसइँयौं/भरसइँयउं/भरसइँयोँ/भरसइँयौँ/भरसइँयउँ, भरसइंयनों/भरसइंयनउं/भरसइंयनौं/भरसइंयनोँ/भरसइंयनउँ/भरसइंयनौँ/भरसइँयनोँ/भरसइँयनउँ/भरसइँयनौँ/भरसइँयनों/भरसइँयनउं/भरसइँयनौं, भरसइंयों/भरसइंयौं/भरसइंयउं/भरसइंयोँ/भरसइंयौँ/भरसइंयउँ/भरसइँयों/भरसइँयौं/भरसइँयउं/भरसइँयोँ/भरसइँयौँ/भरसइँयउँ, भरसइंयनों/भरसइंयनउं/भरसइंयनौं/भरसइंयनोँ/भरसइंयनउँ/भरसइंयनौँ/भरसइँयनोँ/भरसइँयनउँ/भरसइँयनौँ/भरसइँयनों/भरसइँयनउं/भरसइँयनौं</word_forms></word></sequence><sequence value="भौंव"><word><root>भौंवां</root><category>Noun_f_rednt_e1</category><word_forms>भौंवों/भौँवोँ/भौंवउं/भौँवउँ/भौंवौं/भौँवौँ/भौंवोँ/भौँवों/भौंवउँ/भौँवं/भौंवौँ/भौँवौं, भौंवनो/भोँवनो/भौंवनउ/भोँवनउ/भौंवनौ/भोँवनौ, भौंवों/भौँवोँ/भौंवउं/भौँवउँ/भौंवौं/भौँवौँ/भौंवोँ/भौँवों/भौंवउँ/भौँवं/भौंवौँ/भौँवौं, भौंवनो/भोँवनो/भौंवनउ/भोँवनउ/भौंवनौ/भोँवनौ</word_forms></word></sequence><sequence value="फोटोंइय"><word><root>फोटों</root><category>Noun_f_rednt_e1</category><word_forms>फोटोंइयों/फोटोँइयोँ/फोटोंइयोँ/फोटोँइयों/फोटोंइयौं/फोटोँइयौँ/फोटोंइयौँ/फोटोँइयौं/फोटोंइयउं/फोटोँइयउँ/फोटोंइयउँ/फोटोँइयउं, फोटोंइयों/फोटोँइयोँ/फोटोंइयोँ/फोटोँइयों/फोटोंइयौं/फोटोँइयौँ/फोटोंइयौँ/फोटोँइयौं/फोटोंइयउं/फोटोँइयउँ/फोटोंइयउँ/फोटोँइयउं, फोटोंइयों/फोटोँइयोँ/फोटोंइयोँ/फोटोँइयों/फोटोंइयौं/फोटोँइयौँ/फोटोंइयौँ/फोटोँइयौं/फोटोंइयउं/फोटोँइयउँ/फोटोंइयउँ/फोटोँइयउं, फोटोंइयनो/फोटोँइयनो/फोटोंइयनौ/फोटोँइयनौ/फोटोंइयनउ/फोटोँइयनउ</word_forms></word></sequence><sequence value="भुइंय"><word><root>भुइंयां</root><category>Noun_f_rednt_e1</category><word_forms>भुइंयों/भुइँयोँ/भुइंयोँ/भुइँयों/भुइंयउं/भुइँयउँ/भुइंयउँ/भुइँयउं/भुइंयौं/भुइँयौँ/भुइंयौँ/भुइँयौं, भुइंयनउ/भुइँयनउ/भुइंयनौ/भुइँयनौ/भुइंयनो/भुइँयनो, भुइंयों/भुइँयोँ/भुइंयोँ/भुइँयों/भुइंयउं/भुइँयउँ/भुइंयउँ/भुइँयउं/भुइंयौं/भुइँयौँ/भुइंयौँ/भुइँयौं, भुइंयनउ/भुइँयनउ/भुइंयनौ/भुइँयनौ/भुइंयनो/भुइँयनो</word_forms></word></sequence><sequence value="फोटोइय"><word><root>फोटोइया</root><category>Noun_f_rednt_e1</category><word_forms>फोटोइयो/फोटोइयउ/फोटोइऔ, फोटोइयो/फोटोइयउ/फोटोइऔ, फोटोइयो/फोटोइयउ/फोटोइऔ, फोटोइयनो/फोट्यनउ/फोटनौ</word_forms></word></sequence></common_sequences>